amle_py/__init__.py
amle_py/amle_python_interface.py
amle_py/libamle_c.so
amle_py/DLL/32Bit/SDL.dll
amle_py/DLL/32Bit/amle_c-32.dll
amle_py/DLL/64Bit/SDL.dll
amle_py/DLL/64Bit/amle_c-64.dll
amle_py/data/SupportedGames/arkanoid.data
amle_py/data/SupportedGames/buggy.data
amle_py/data/resources/audio.bmp
amle_py/data/resources/cap32logo.bmp
amle_py/data/resources/disk.bmp
amle_py/data/resources/general.bmp
amle_py/data/resources/input.bmp
amle_py/data/resources/keymap_es_linux.map
amle_py/data/resources/keymap_es_win.map
amle_py/data/resources/keymap_fr_linux.map
amle_py/data/resources/keymap_fr_win.map
amle_py/data/resources/keymap_uk_linux.map
amle_py/data/resources/keymap_uk_win.map
amle_py/data/resources/keymap_us.map
amle_py/data/resources/rom.bmp
amle_py/data/resources/vera_mono.ttf
amle_py/data/resources/vera_sans.ttf
amle_py/data/resources/video.bmp
amle_py/data/resources/freedesktop/Emulators.directory
amle_py/data/resources/freedesktop/caprice32.desktop
amle_py/data/resources/freedesktop/caprice32.menu
amle_py/data/resources/freedesktop/caprice32.png
amle_py/data/resources/freedesktop/emulators.png
amle_py/data/rom/MF2.rom
amle_py/data/rom/amsdos.rom
amle_py/data/rom/cpc464.rom
amle_py/data/rom/cpc6128.rom
amle_py/data/rom/cpc664.rom
amle_py/data/rom/system.cpr
amle_py-1.1.5.dist-info/DESCRIPTION.rst
amle_py-1.1.5.dist-info/METADATA
amle_py-1.1.5.dist-info/RECORD
amle_py-1.1.5.dist-info/WHEEL
amle_py-1.1.5.dist-info/metadata.json
amle_py-1.1.5.dist-info/top_level.txt
