Metadata-Version: 2.0
Name: amle-py
Version: 1.1.5
Summary: A package that can be used to make an AI learn from Amstrad CPC games.
Home-page: https://github.com/pypa/sampleproject
Author: Theo De castro Pinto
Author-email: decastrotheo960@gmail.com
License: UNKNOWN
Platform: UNKNOWN
Classifier: Programming Language :: Python :: 3
Classifier: License :: OSI Approved :: MIT License
Classifier: Operating System :: OS Independent
Requires-Python: >=3.6
